mem_vault/__init__.py
mem_vault/exceptions.py
mem_vault/memory.py
mem_vault/storage.py
mem_vault/utils.py
mem_vault-0.1.1.dist-info/LICENSE
mem_vault-0.1.1.dist-info/METADATA
mem_vault-0.1.1.dist-info/WHEEL
mem_vault-0.1.1.dist-info/top_level.txt
mem_vault-0.1.1.dist-info/RECORD
