Metadata-Version: 2.2
Name: mem_vault
Version: 0.1.1
Summary: A library for storing and retrieving embeddings with PGVector (with Chunking)
Home-page: https://github.com/Instadeploy/mem-vault
Author: Jitin Pillai
Author-email: me@jitinpillai.com
Classifier: Programming Language :: Python :: 3
Classifier: License :: OSI Approved :: MIT License
Classifier: Operating System :: OS Independent
Requires-Python: >=3.7
License-File: LICENSE
Requires-Dist: numpy>=1.19.0
Requires-Dist: openai>=1.0.0
Requires-Dist: sqlalchemy>=1.4.0
Requires-Dist: psycopg2-binary>=2.9.0
Requires-Dist: pgvector>=0.2.0
Requires-Dist: regex>=2023.0.0
Provides-Extra: django
Requires-Dist: django>=3.2; extra == "django"
Dynamic: author
Dynamic: author-email
Dynamic: classifier
Dynamic: description
Dynamic: description-content-type
Dynamic: home-page
Dynamic: provides-extra
Dynamic: requires-dist
Dynamic: requires-python
Dynamic: summary
